hvwfg/__init__.py
hvwfg/hv4dr.cpython-36m-x86_64-linux-gnu.so
hvwfg/_version.py
hvwfg/hv5dr.cpython-36m-x86_64-linux-gnu.so
hvwfg/wfg.cpython-36m-x86_64-linux-gnu.so
hvwfg-1.0.2.dist-info/METADATA
hvwfg-1.0.2.dist-info/WHEEL
hvwfg-1.0.2.dist-info/top_level.txt
hvwfg-1.0.2.dist-info/RECORD
hvwfg-1.0.2.dist-info/LICENSE
