Metadata-Version: 2.1
Name: hvwfg
Version: 1.0.2
Summary: Python wrapper of the WFG hypervolume calculation functions
Home-page: https://github.com/epfl-lamd/hvwfg
Author: Cyril Picard
Author-email: cyril.picard@epfl.ch
License: GPL3
Project-URL: Bug Reports, https://github.com/epfl-lamd/hvwfg/issues
Project-URL: Source, https://github.com/epfl-lamd/hvwfg
Platform: UNKNOWN
Classifier: Development Status :: 5 - Production/Stable
Classifier: Intended Audience :: Science/Research
Classifier: Topic :: Scientific/Engineering
Classifier: Programming Language :: Python :: 3.5
Classifier: Programming Language :: Python :: 3.6
Classifier: Programming Language :: Python :: 3.7
